loghooks/__init__.py
loghooks/handler.py
loghooks/webhooks.py
loghooks-0.2.0.dist-info/METADATA
loghooks-0.2.0.dist-info/WHEEL
loghooks-0.2.0.dist-info/top_level.txt
loghooks-0.2.0.dist-info/RECORD
